castle.cms-2.25.0-py2.7-nspkg.pth
castle/cms/__init__.py
castle/cms/archival.py
castle/cms/audit.py
castle/cms/authentication.py
castle/cms/cache.py
castle/cms/commands.py
castle/cms/compat.py
castle/cms/configure.zcml
castle/cms/constants.py
castle/cms/defaults.py
castle/cms/events.py
castle/cms/gelf.py
castle/cms/impersonator.py
castle/cms/indexers.py
castle/cms/indexing.zcml
castle/cms/install.py
castle/cms/jbot.py
castle/cms/ld.py
castle/cms/lead.py
castle/cms/linkintegrity.py
castle/cms/linkreporter.py
castle/cms/locking.py
castle/cms/lockout.py
castle/cms/logger.py
castle/cms/meta.zcml
castle/cms/metaconfiguration.py
castle/cms/overrides.zcml
castle/cms/package.py
castle/cms/patches.py
castle/cms/patches.zcml
castle/cms/patterns.py
castle/cms/profile.zcml
castle/cms/redirects.py
castle/cms/registration.py
castle/cms/registry.py
castle/cms/search.py
castle/cms/security.py
castle/cms/settings.py
castle/cms/shield.py
castle/cms/social.py
castle/cms/static.zcml
castle/cms/statusmessages.py
castle/cms/stringinterp.py
castle/cms/subscribe.py
castle/cms/subscribers.py
castle/cms/subscribers.zcml
castle/cms/syndication.py
castle/cms/taskinfo.py
castle/cms/testing.py
castle/cms/texting.py
castle/cms/theming.py
castle/cms/theming.zcml
castle/cms/toolbar.py
castle/cms/transformer.py
castle/cms/trash.py
castle/cms/traverser.py
castle/cms/ua.py
castle/cms/unconfigure.zcml
castle/cms/upgrades.zcml
castle/cms/vhm.py
castle/cms/vocabularies.py
castle/cms/widgets.py
castle/cms/widgets.zcml
castle/cms/_scripts/__init__.py
castle/cms/_scripts/cleanup_archive.py
castle/cms/_scripts/create-site.py
castle/cms/_scripts/export-archives.py
castle/cms/_scripts/export-content.py
castle/cms/_scripts/find-broken-links.py
castle/cms/_scripts/importarchives.py
castle/cms/_scripts/importjson.py
castle/cms/_scripts/importtypes.py
castle/cms/_scripts/init-dev.py
castle/cms/_scripts/latest-modified.py
castle/cms/_scripts/mjson.py
castle/cms/_scripts/process-pdfs.py
castle.cms-2.25.0.dist-info/LICENSE
castle.cms-2.25.0.dist-info/METADATA
castle.cms-2.25.0.dist-info/WHEEL
castle.cms-2.25.0.dist-info/entry_points.txt
castle.cms-2.25.0.dist-info/namespace_packages.txt
castle.cms-2.25.0.dist-info/top_level.txt
castle.cms-2.25.0.dist-info/RECORD
