Metadata-Version: 2.1
Name: castle.cms
Version: 2.25.0
Summary: CastleCMS Plone distribution main package
Home-page: https://github.com/castlecms/castle.cms
Author: Wildcard Corp
Author-email: info@wildcardcorp.com
License: GPL2
Keywords: plone cms castle
Platform: UNKNOWN
Classifier: Programming Language :: Python
Classifier: Programming Language :: Python :: 2.7
Classifier: Framework :: Plone :: 5.0
Classifier: Framework :: Plone
Classifier: Framework :: Plone :: 5.1
Classifier: Framework :: CastleCMS
Classifier: Framework :: CastleCMS :: Theme
Requires-Dist: Products.CMFPlone (>=5.0.10)
Requires-Dist: mockup (>=2.4.2.dev1)
Requires-Dist: plone.app.upgrade (>=2.0.17)
Requires-Dist: plone.app.mosaic (>=2.0.0.dev24)
Requires-Dist: plone.app.blocks (>=10.0.0)
Requires-Dist: Products.PloneKeywordManager (>=2.2.1)
Requires-Dist: plone.schemaeditor (>=2.0.18)
Requires-Dist: plone.namedfile (>=3.0.10)
Requires-Dist: plone.folder (>=1.0.12)
Requires-Dist: AccessControl (>=3.0.14)
Requires-Dist: z3c.relationfield (>=0.7.1.dev0)
Requires-Dist: Products.ZCatalog (>=3.0.3dev2)
Requires-Dist: plone.app.standardtiles (>=2.0.0.dev0)
Requires-Dist: plone.stringinterp (>=1.3.1)
Requires-Dist: Products.CMFPlacefulWorkflow
Requires-Dist: plone.app.caching
Requires-Dist: plone.app.dexterity
Requires-Dist: plone.app.iterate
Requires-Dist: plone.api
Requires-Dist: castle.theme (>=1.0.6)
Requires-Dist: collective.documentviewer (>=5.0.4)
Requires-Dist: collective.elasticsearch (<3,>=2.0.5)
Requires-Dist: collective.celery (>=1.1.4)
Requires-Dist: boto3 (>=1.9.222)
Requires-Dist: google-api-python-client (<2,>=1.4.2)
Requires-Dist: google-auth (>=2.5.0)
Requires-Dist: requests (<3,>=2.7.0)
Requires-Dist: requests-oauthlib (<1,>=0.5.0)
Requires-Dist: oauth2client (<2,>=1.5.1)
Requires-Dist: redis (<3,>=2.10.5)
Requires-Dist: setuptools
Requires-Dist: python-dateutil
Requires-Dist: pyopenssl
Requires-Dist: phonenumbers
Requires-Dist: html2text
Requires-Dist: pycountry
Requires-Dist: tendo
Requires-Dist: pylru
Requires-Dist: sqlalchemy
Requires-Dist: z3c.unconfigure
Requires-Dist: z3c.jbot
Provides-Extra: development
Requires-Dist: zest.releaser ; extra == 'development'
Requires-Dist: check-manifest ; extra == 'development'
Provides-Extra: forms
Requires-Dist: collective.easyform[recaptcha] ; extra == 'forms'
Provides-Extra: profile
Requires-Dist: collective.profiler ; extra == 'profile'
Provides-Extra: test
Requires-Dist: plone.app.testing ; extra == 'test'
Requires-Dist: responses ; extra == 'test'
Requires-Dist: mock ; extra == 'test'
Requires-Dist: argon2-cffi ; extra == 'test'
Requires-Dist: plone.app.robotframework ; extra == 'test'
Requires-Dist: moto ; extra == 'test'
